setup.py
gauss_bin_distr/Binomialdistribution.py
gauss_bin_distr/Gaussiandistribution.py
gauss_bin_distr/Generaldistribution.py
gauss_bin_distr/__init__.py
gauss_bin_distr.egg-info/PKG-INFO
gauss_bin_distr.egg-info/SOURCES.txt
gauss_bin_distr.egg-info/dependency_links.txt
gauss_bin_distr.egg-info/not-zip-safe
gauss_bin_distr.egg-info/top_level.txt