Metadata-Version: 1.0
Name: gauss-bin-distr
Version: 1.1
Summary: Gaussian and Binomial distributions
Home-page: UNKNOWN
Author: Kariuki Samuel
Author-email: samuelkariuki544@gmail.com
License: UNKNOWN
Platform: UNKNOWN
